NiukeShichangGangQiuzhiJingyanFenxiang20212022/README.md
NiukeShichangGangQiuzhiJingyanFenxiang20212022/__init__.py
NiukeShichangGangQiuzhiJingyanFenxiang20212022/__main__.py
NiukeShichangGangQiuzhiJingyanFenxiang20212022/file.epub
NiukeShichangGangQiuzhiJingyanFenxiang20212022/index.html
NiukeShichangGangQiuzhiJingyanFenxiang20212022/css/__init__.py
NiukeShichangGangQiuzhiJingyanFenxiang20212022/css/annotations.css
NiukeShichangGangQiuzhiJingyanFenxiang20212022/css/main.css
NiukeShichangGangQiuzhiJingyanFenxiang20212022/css/normalize.css
NiukeShichangGangQiuzhiJingyanFenxiang20212022/css/popup.css
NiukeShichangGangQiuzhiJingyanFenxiang20212022/font/__init__.py
NiukeShichangGangQiuzhiJingyanFenxiang20212022/font/fontello.eot
NiukeShichangGangQiuzhiJingyanFenxiang20212022/font/fontello.svg
NiukeShichangGangQiuzhiJingyanFenxiang20212022/font/fontello.ttf
NiukeShichangGangQiuzhiJingyanFenxiang20212022/font/fontello.woff
NiukeShichangGangQiuzhiJingyanFenxiang20212022/img/__init__.py
NiukeShichangGangQiuzhiJingyanFenxiang20212022/img/annotator-glyph-sprite.png
NiukeShichangGangQiuzhiJingyanFenxiang20212022/img/annotator-icon-sprite.png
NiukeShichangGangQiuzhiJingyanFenxiang20212022/img/apple-touch-icon.png
NiukeShichangGangQiuzhiJingyanFenxiang20212022/img/cancelfullscreen.png
NiukeShichangGangQiuzhiJingyanFenxiang20212022/img/close.png
NiukeShichangGangQiuzhiJingyanFenxiang20212022/img/fullscreen.png
NiukeShichangGangQiuzhiJingyanFenxiang20212022/img/loader.gif
NiukeShichangGangQiuzhiJingyanFenxiang20212022/img/menu-icon.png
NiukeShichangGangQiuzhiJingyanFenxiang20212022/img/save.png
NiukeShichangGangQiuzhiJingyanFenxiang20212022/img/saved.png
NiukeShichangGangQiuzhiJingyanFenxiang20212022/img/settings-s.png
NiukeShichangGangQiuzhiJingyanFenxiang20212022/img/settings.png
NiukeShichangGangQiuzhiJingyanFenxiang20212022/img/star.png
NiukeShichangGangQiuzhiJingyanFenxiang20212022/js/__init__.py
NiukeShichangGangQiuzhiJingyanFenxiang20212022/js/epub.js
niuke_shichang_gang_qiuzhi_jingyan_fenxiang_2021_2022-2024.3.6.0.dist-info/METADATA
niuke_shichang_gang_qiuzhi_jingyan_fenxiang_2021_2022-2024.3.6.0.dist-info/WHEEL
niuke_shichang_gang_qiuzhi_jingyan_fenxiang_2021_2022-2024.3.6.0.dist-info/entry_points.txt
niuke_shichang_gang_qiuzhi_jingyan_fenxiang_2021_2022-2024.3.6.0.dist-info/top_level.txt
niuke_shichang_gang_qiuzhi_jingyan_fenxiang_2021_2022-2024.3.6.0.dist-info/RECORD
